robbuffet/__init__.py
robbuffet/calibration.py
robbuffet/data.py
robbuffet/decision.py
robbuffet/region.py
robbuffet/scores.py
robbuffet/vis.py
robbuffet-0.2.dist-info/licenses/LICENSE
robbuffet-0.2.dist-info/METADATA
robbuffet-0.2.dist-info/WHEEL
robbuffet-0.2.dist-info/top_level.txt
robbuffet-0.2.dist-info/RECORD
