Metadata-Version: 2.4
Name: robbuffet
Version: 0.2
Summary: Conformal prediction and robust decision-making toolkit (PyTorch + CVXPY)
Author: Yash Patel
License-Expression: MIT
Project-URL: homepage, https://github.com/yashpatel5400/robbuffet
Project-URL: repository, https://github.com/yashpatel5400/robbuffet
Classifier: Programming Language :: Python :: 3
Classifier: Intended Audience :: Science/Research
Classifier: Topic :: Scientific/Engineering :: Artificial Intelligence
Classifier: Topic :: Scientific/Engineering :: Mathematics
Requires-Python: >=3.10
License-File: LICENSE
Requires-Dist: numpy>=1.24
Requires-Dist: torch>=2.1.0
Requires-Dist: cvxpy>=1.4.0
Requires-Dist: matplotlib>=3.7.0
Requires-Dist: networkx>=2.8
Provides-Extra: dev
Requires-Dist: pytest>=7.4.0; extra == "dev"
Requires-Dist: build>=1.0.0; extra == "dev"
Requires-Dist: twine>=4.0.0; extra == "dev"
Dynamic: license-file
